quaternions/__init__.py
quaternions/general_quaternion.py
quaternions/quaternion.py
quaternions/utils.py
satellogic_quaternions-0.1.8.dist-info/METADATA
satellogic_quaternions-0.1.8.dist-info/WHEEL
satellogic_quaternions-0.1.8.dist-info/licenses/LICENSE
satellogic_quaternions-0.1.8.dist-info/RECORD
