Metadata-Version: 2.4
Name: satellogic_quaternions
Version: 0.1.8
Summary: This is a library for dealing with quaternions in Python in a unified way.
Project-URL: Homepage, https://pypi.org/project/satellogic_quaternions
Project-URL: Repository, https://github.com/satellogic/quaternions
Author-email: Matias Graña <matias@satellogic.com>
License: GPLv3
License-File: LICENSE
Classifier: Development Status :: 4 - Beta
Classifier: Environment :: Console
Classifier: Intended Audience :: Science/Research
Classifier: Operating System :: OS Independent
Classifier: Programming Language :: Python
Classifier: Topic :: Software Development :: Libraries :: Python Modules
Classifier: Topic :: Utilities
Requires-Python: >=3.4
Requires-Dist: numpy
Provides-Extra: dev
Requires-Dist: coveralls; extra == 'dev'
Requires-Dist: flake8>=2.5.4; extra == 'dev'
Requires-Dist: hypothesis; extra == 'dev'
Requires-Dist: pytest; extra == 'dev'
Requires-Dist: pytest-coverage; extra == 'dev'
